makeocr/__init__.py
makeocr/ocr.py
makeocr-0.0.1.dist-info/LICENSE
makeocr-0.0.1.dist-info/METADATA
makeocr-0.0.1.dist-info/WHEEL
makeocr-0.0.1.dist-info/top_level.txt
makeocr-0.0.1.dist-info/RECORD
